humanfirst/__init__.py
humanfirst/apis.py
humanfirst/authorization.py
humanfirst/generators.py
humanfirst/nlg.py
humanfirst/objects.py
humanfirst/config/logging.conf
humanfirst/config/setup.cfg
tests/__init__.py
tests/humanfirst_test.py
humanfirst-2.2.0.dist-info/LICENSE
humanfirst-2.2.0.dist-info/METADATA
humanfirst-2.2.0.dist-info/WHEEL
humanfirst-2.2.0.dist-info/top_level.txt
humanfirst-2.2.0.dist-info/RECORD
