Metadata-Version: 2.1
Name: humanfirst
Version: 2.2.0
Summary: HumanFirst Package Module
Home-page: https://humanfirst.ai
Author: Mohammed Fayaz Ansar Jelani
Author-email: fayaz@humanfirst.ai
License: MIT
Project-URL: Documentation, https://docs.humanfirst.ai/docs/
Project-URL: Source, https://github.com/zia-ai/humanfirst-module
Keywords: python,humanfirst,HumanFirst
Platform: UNKNOWN
Classifier: Development Status :: 5 - Production/Stable
Classifier: Programming Language :: Python :: 3.11
Classifier: Operating System :: OS Independent
Requires-Python: >=3.8
License-File: LICENSE
Requires-Dist: numpy
Requires-Dist: pandas
Requires-Dist: requests
Requires-Dist: requests-toolbelt
Requires-Dist: dataclasses
Requires-Dist: dataclasses-json
Requires-Dist: python-dotenv
Requires-Dist: PyJWT[crypto]
Requires-Dist: protobuf
Provides-Extra: dev
Requires-Dist: twine ==5.1.1 ; extra == 'dev'
Requires-Dist: wheel ==0.41.2 ; extra == 'dev'
Requires-Dist: keyring ; extra == 'dev'
Requires-Dist: keyrings.alt ; extra == 'dev'
Requires-Dist: pylint ; extra == 'dev'
Requires-Dist: git-pylint-commit-hook ; extra == 'dev'
Requires-Dist: numpy ; extra == 'dev'
Requires-Dist: pandas ; extra == 'dev'
Requires-Dist: requests ; extra == 'dev'
Requires-Dist: requests-toolbelt ; extra == 'dev'
Requires-Dist: autopep8 ; extra == 'dev'
Requires-Dist: dataclasses ; extra == 'dev'
Requires-Dist: dataclasses-json ; extra == 'dev'
Requires-Dist: pytest ; extra == 'dev'
Requires-Dist: python-dotenv ; extra == 'dev'
Requires-Dist: pytest-cov ; extra == 'dev'
Requires-Dist: ntplib ; extra == 'dev'
Requires-Dist: PyJWT[crypto] ; extra == 'dev'
